agent_framework_azurefunctions-0.0.1.dist-info/licenses/LICENSE
durableagent/__init__.py
durableagent/app.py
durableagent/callbacks.py
durableagent/entities.py
durableagent/errors.py
durableagent/logging_config.py
durableagent/models.py
durableagent/orchestration.py
durableagent/state.py
agent_framework_azurefunctions-0.0.1.dist-info/METADATA
agent_framework_azurefunctions-0.0.1.dist-info/WHEEL
agent_framework_azurefunctions-0.0.1.dist-info/top_level.txt
agent_framework_azurefunctions-0.0.1.dist-info/RECORD
