Metadata-Version: 2.4
Name: agent-framework-azurefunctions
Version: 0.0.1
Summary: Durable Agent Framework - Deploy Microsoft Agent Framework agents as Azure Durable Function Apps using Durable Entities
Author-email: Microsoft <azurefunctions@microsoft.com>
License: MIT
Project-URL: Homepage, https://github.com/Azure/durable-agent-framework
Project-URL: Documentation, https://github.com/Azure/durable-agent-framework/tree/main/python#readme
Project-URL: Repository, https://github.com/Azure/durable-agent-framework
Project-URL: Issues, https://github.com/Azure/durable-agent-framework/issues
Keywords: azure,functions,durable,entity,agent,ai,microsoft,agent-framework,azure-functions
Classifier: Development Status :: 3 - Alpha
Classifier: Intended Audience :: Developers
Classifier: License :: OSI Approved :: MIT License
Classifier: Programming Language :: Python :: 3
Classifier: Programming Language :: Python :: 3.10
Classifier: Programming Language :: Python :: 3.11
Classifier: Programming Language :: Python :: 3.12
Classifier: Programming Language :: Python :: 3.13
Classifier: Topic :: Software Development :: Libraries :: Python Modules
Classifier: Topic :: Scientific/Engineering :: Artificial Intelligence
Requires-Python: >=3.10
License-File: LICENSE
Requires-Dist: azure-functions
Requires-Dist: azure-functions-durable
Requires-Dist: agent-framework
Requires-Dist: pytest>=8.4.2
Requires-Dist: pytest-asyncio>=1.2.0
Provides-Extra: dev
Requires-Dist: pytest>=7.0.0; extra == "dev"
Requires-Dist: pytest-asyncio>=0.21.0; extra == "dev"
Requires-Dist: pytest-cov>=4.0.0; extra == "dev"
Provides-Extra: azure-openai
Requires-Dist: azure-identity>=1.15.0; extra == "azure-openai"
Requires-Dist: openai>=1.0.0; extra == "azure-openai"
Provides-Extra: azure-ai
Requires-Dist: azure-ai-projects>=1.0.0; extra == "azure-ai"
Requires-Dist: azure-identity>=1.15.0; extra == "azure-ai"
Dynamic: license-file
